csolver-0.7.0.dist-info/METADATA
csolver-0.7.0.dist-info/WHEEL
csolver/__init__.py
csolver/__version__.py
csolver/check_captcha.py
csolver/lib/__init__.py
csolver/lib/common.onnx
csolver/lib/common_det.onnx
csolver/lib/common_old.onnx
csolver/read_captcha.py
csolver-0.7.0.dist-info/RECORD
